{
    "nickname": "小绿",
    "id": 2003,
    "blood": 0,
    "attack": 105,
    "defense": 0,
    "attack_speed": 0.8,
    "attack_crit": 0,
    "move_speed": 0,
    "skill": [9001],
    "attack_type": 0,
    "attack_spark": 0,
    "attack_targets": 0,
    "attack_effnum": 0,
    "attack_number": 1,
    "attack_number_grop": 0,
    "blood_grow": 0,
    "attack_grow": 2,
    "defense_grow": 0,
    "attack_speed_grop": 0,
    "attack_crit_grop": 0,
    "attack_targets_grop": 0,
    "attack_effnum_grop": 0
}